web_skeleton3/__init__.py
web_skeleton3/main.py
web_skeleton3/assets/README.txt
web_skeleton3/assets/h5bp/404.html
web_skeleton3/assets/h5bp/browserconfig.xml
web_skeleton3/assets/h5bp/favicon.ico
web_skeleton3/assets/h5bp/humans.txt
web_skeleton3/assets/h5bp/icon.png
web_skeleton3/assets/h5bp/robots.txt
web_skeleton3/assets/h5bp/site.webmanifest
web_skeleton3/assets/h5bp/tile-wide.png
web_skeleton3/assets/h5bp/tile.png
web_skeleton3/assets/h5bp/static/h5bp/css/main.css
web_skeleton3/assets/h5bp/static/h5bp/css/normalize.css
web_skeleton3/assets/h5bp/static/h5bp/js/modernizr.js
web_skeleton3/assets/h5bp/static/h5bp/js/plugins.js
web_skeleton3/assets/logo/favicon.ico
web_skeleton3/assets/logo/genera_apple_icons.sh
web_skeleton3/assets/logo/icon.png
web_skeleton3/assets/logo/sample.svg
web_skeleton3/assets/logo/tile-wide.png
web_skeleton3/assets/logo/tile.png
web_skeleton3/code/config.json
web_skeleton3/code/index.mako
web_skeleton3/code/app/sample.js
web_skeleton3/code/scss-mixins/README.txt
web_skeleton3/setup/.gitignore
web_skeleton3/setup/Makefile
web_skeleton3/setup/README.rst
web_skeleton3/setup/watch.json
web_skeleton3/setup/watch.sh
web_skeleton3/setup/web-skeleton3.ini
web_skeleton3-2.1.3.dist-info/entry_points.txt
web_skeleton3-2.1.3.dist-info/LICENSE.txt
web_skeleton3-2.1.3.dist-info/WHEEL
web_skeleton3-2.1.3.dist-info/METADATA
web_skeleton3-2.1.3.dist-info/RECORD
