Metadata-Version: 2.1
Name: web_skeleton3
Version: 2.1.3
Summary: Static html code generator.
Author-email: rmm <rosa.martinez@artgins.com>
Requires-Python: >=3.8
Classifier: Intended Audience :: Developers
Classifier: Development Status :: 5 - Production/Stable
Classifier: Environment :: Console
Classifier: Programming Language :: Python
Classifier: Programming Language :: Python :: 3
Classifier: License :: OSI Approved :: MIT License
Classifier: Topic :: Internet :: WWW/HTTP
Classifier: Topic :: Software Development :: Libraries
Requires-Dist: rjsmin
Requires-Dist: cssutils
Requires-Dist: mako
Requires-Dist: webassets
Requires-Dist: delegator.py
Project-URL: Homepage, https://github.com/artgins/web-skeleton3
